django_wordpress_rest-0.1.3.dist-info/DESCRIPTION.rst
django_wordpress_rest-0.1.3.dist-info/METADATA
django_wordpress_rest-0.1.3.dist-info/metadata.json
django_wordpress_rest-0.1.3.dist-info/pbr.json
django_wordpress_rest-0.1.3.dist-info/RECORD
django_wordpress_rest-0.1.3.dist-info/top_level.txt
django_wordpress_rest-0.1.3.dist-info/WHEEL
wordpress/__init__.py
wordpress/admin.py
wordpress/loading.py
wordpress/models.py
wordpress/urls.py
wordpress/utils.py
wordpress/views.py
wordpress/management/__init__.py
wordpress/management/commands/__init__.py
wordpress/management/commands/load_wp_api.py
wordpress/tests/__init__.py
wordpress/tests/test_loading.py
