Metadata-Version: 2.0
Name: django-wordpress-rest
Version: 0.1.3
Summary: Sync a WordPress site to Django via the WordPress.com REST API
Home-page: https://github.com/observermedia/django-wordpress-rest
Author: Observer Media
Author-email: jsternberg@observer.com
License: MIT
Keywords: django wordpress wordpress.com REST API
Platform: UNKNOWN
Classifier: Development Status :: 4 - Beta
Classifier: Environment :: Web Environment
Classifier: Framework :: Django
Classifier: Intended Audience :: Developers
Classifier: License :: OSI Approved :: MIT License
Classifier: Operating System :: OS Independent
Classifier: Programming Language :: Python
Classifier: Programming Language :: Python :: 2
Classifier: Programming Language :: Python :: 3
Classifier: Topic :: Software Development :: Libraries :: Python Modules
Requires-Dist: Django (>=1.7.9)
Requires-Dist: django-after-response (==0.2.1)
Requires-Dist: jsonfield (>=1.0.3)
Requires-Dist: python-dateutil (>=2.4.2)
Requires-Dist: requests (>=2.7.0)
Requires-Dist: six (>=1.9.0)
